botbuilder/dialogs/__init__.py
botbuilder/dialogs/_user_token_access.py
botbuilder/dialogs/about.py
botbuilder/dialogs/component_dialog.py
botbuilder/dialogs/dialog.py
botbuilder/dialogs/dialog_container.py
botbuilder/dialogs/dialog_context.py
botbuilder/dialogs/dialog_event.py
botbuilder/dialogs/dialog_events.py
botbuilder/dialogs/dialog_extensions.py
botbuilder/dialogs/dialog_instance.py
botbuilder/dialogs/dialog_manager.py
botbuilder/dialogs/dialog_manager_result.py
botbuilder/dialogs/dialog_reason.py
botbuilder/dialogs/dialog_set.py
botbuilder/dialogs/dialog_state.py
botbuilder/dialogs/dialog_turn_result.py
botbuilder/dialogs/dialog_turn_status.py
botbuilder/dialogs/dialogs_component_registration.py
botbuilder/dialogs/object_path.py
botbuilder/dialogs/persisted_state.py
botbuilder/dialogs/persisted_state_keys.py
botbuilder/dialogs/waterfall_dialog.py
botbuilder/dialogs/waterfall_step.py
botbuilder/dialogs/waterfall_step_context.py
botbuilder/dialogs/choices/__init__.py
botbuilder/dialogs/choices/channel.py
botbuilder/dialogs/choices/choice.py
botbuilder/dialogs/choices/choice_factory.py
botbuilder/dialogs/choices/choice_factory_options.py
botbuilder/dialogs/choices/choice_recognizers.py
botbuilder/dialogs/choices/find.py
botbuilder/dialogs/choices/find_choices_options.py
botbuilder/dialogs/choices/find_values_options.py
botbuilder/dialogs/choices/found_choice.py
botbuilder/dialogs/choices/found_value.py
botbuilder/dialogs/choices/list_style.py
botbuilder/dialogs/choices/model_result.py
botbuilder/dialogs/choices/sorted_value.py
botbuilder/dialogs/choices/token.py
botbuilder/dialogs/choices/tokenizer.py
botbuilder/dialogs/memory/__init__.py
botbuilder/dialogs/memory/component_memory_scopes_base.py
botbuilder/dialogs/memory/component_path_resolvers_base.py
botbuilder/dialogs/memory/dialog_path.py
botbuilder/dialogs/memory/dialog_state_manager.py
botbuilder/dialogs/memory/dialog_state_manager_configuration.py
botbuilder/dialogs/memory/path_resolver_base.py
botbuilder_dialogs-4.17.1.dist-info/METADATA
botbuilder_dialogs-4.17.1.dist-info/WHEEL
botbuilder_dialogs-4.17.1.dist-info/top_level.txt
botbuilder_dialogs-4.17.1.dist-info/RECORD
