Metadata-Version: 2.1
Name: botbuilder-dialogs
Version: 4.17.1
Summary: Microsoft Bot Framework Bot Builder
Home-page: https://www.github.com/Microsoft/botbuilder-python
Author: Microsoft
License: MIT
Keywords: BotBuilderDialogs,bots,ai,botframework,botbuilder
Classifier: Programming Language :: Python :: 3.7
Classifier: Intended Audience :: Developers
Classifier: License :: OSI Approved :: MIT License
Classifier: Operating System :: OS Independent
Classifier: Development Status :: 5 - Production/Stable
Classifier: Topic :: Scientific/Engineering :: Artificial Intelligence
Requires-Dist: regex>=2022.1.18
Requires-Dist: emoji==1.7.0
Requires-Dist: recognizers-text-date-time>=1.0.2a1
Requires-Dist: recognizers-text-number-with-unit>=1.0.2a1
Requires-Dist: recognizers-text-number>=1.0.2a1
Requires-Dist: recognizers-text>=1.0.2a1
Requires-Dist: recognizers-text-choice>=1.0.2a1
Requires-Dist: babel==2.9.1
Requires-Dist: botbuilder-schema==4.17.1
Requires-Dist: botframework-connector==4.17.1
Requires-Dist: botbuilder-core==4.17.1
Requires-Dist: aiounittest==1.3.0
